waechter-0.2.4.dist-info/METADATA
waechter-0.2.4.dist-info/metadata.json
waechter-0.2.4.dist-info/WHEEL
waechter-0.2.4.dist-info/DESCRIPTION.rst
waechter-0.2.4.dist-info/RECORD
waechter-0.2.4.dist-info/top_level.txt
waechter/scheduler.py
waechter/__init__.py
