Metadata-Version: 2.0
Name: waechter
Version: 0.2.4
Summary: Job Scheduling Helper
Home-page: https://github.com/glaslos/waechter
Author: Lukas Rist
Author-email: glaslos@gmail.com
License: GPL 3
Platform: UNKNOWN
Classifier: Development Status :: 4 - Beta
Classifier: Environment :: Console
Classifier: Intended Audience :: Developers
Classifier: License :: OSI Approved :: GNU General Public License v3 (GPLv3)
Classifier: Operating System :: POSIX :: Linux
Classifier: Programming Language :: Python
